odoo8_addon_crm_rma_prodlot_supplier-8.0.1.0.0.99.dev23-nspkg.pth
odoo_addons/crm_rma_prodlot_supplier/README.rst
odoo_addons/crm_rma_prodlot_supplier/__init__.py
odoo_addons/crm_rma_prodlot_supplier/__openerp__.py
odoo_addons/crm_rma_prodlot_supplier/i18n/bg.po
odoo_addons/crm_rma_prodlot_supplier/i18n/ca.po
odoo_addons/crm_rma_prodlot_supplier/i18n/crm_rma_prodlot_supplier.pot
odoo_addons/crm_rma_prodlot_supplier/i18n/de.po
odoo_addons/crm_rma_prodlot_supplier/i18n/el_GR.po
odoo_addons/crm_rma_prodlot_supplier/i18n/es.po
odoo_addons/crm_rma_prodlot_supplier/i18n/es_AR.po
odoo_addons/crm_rma_prodlot_supplier/i18n/es_MX.po
odoo_addons/crm_rma_prodlot_supplier/i18n/es_PA.po
odoo_addons/crm_rma_prodlot_supplier/i18n/es_VE.po
odoo_addons/crm_rma_prodlot_supplier/i18n/fi.po
odoo_addons/crm_rma_prodlot_supplier/i18n/fr.po
odoo_addons/crm_rma_prodlot_supplier/i18n/fr_FR.po
odoo_addons/crm_rma_prodlot_supplier/i18n/it.po
odoo_addons/crm_rma_prodlot_supplier/i18n/nl_NL.po
odoo_addons/crm_rma_prodlot_supplier/i18n/pt_BR.po
odoo_addons/crm_rma_prodlot_supplier/i18n/pt_PT.po
odoo_addons/crm_rma_prodlot_supplier/i18n/sk.po
odoo_addons/crm_rma_prodlot_supplier/i18n/sl.po
odoo_addons/crm_rma_prodlot_supplier/i18n/tr.po
odoo_addons/crm_rma_prodlot_supplier/i18n/tr_TR.po
odoo_addons/crm_rma_prodlot_supplier/models/__init__.py
odoo_addons/crm_rma_prodlot_supplier/models/stock_picking.py
odoo_addons/crm_rma_prodlot_supplier/models/stock_production_lot.py
odoo_addons/crm_rma_prodlot_supplier/models/stock_transfer_details.py
odoo_addons/crm_rma_prodlot_supplier/static/description/icon.png
odoo_addons/crm_rma_prodlot_supplier/tests/__init__.py
odoo_addons/crm_rma_prodlot_supplier/tests/test_crm_rma_prodlot_supplier.py
odoo_addons/crm_rma_prodlot_supplier/views/stock_view.xml
odoo8_addon_crm_rma_prodlot_supplier-8.0.1.0.0.99.dev23.dist-info/METADATA
odoo8_addon_crm_rma_prodlot_supplier-8.0.1.0.0.99.dev23.dist-info/WHEEL
odoo8_addon_crm_rma_prodlot_supplier-8.0.1.0.0.99.dev23.dist-info/namespace_packages.txt
odoo8_addon_crm_rma_prodlot_supplier-8.0.1.0.0.99.dev23.dist-info/top_level.txt
odoo8_addon_crm_rma_prodlot_supplier-8.0.1.0.0.99.dev23.dist-info/RECORD
